dependency_injection/__init__.py
dependency_injection/data_structures/__init__.py
dependency_injection/data_structures/dependency_injection_exception.py
dependency_injection/data_structures/dictionary_as_object.py
dependency_injection/decorators/__init__.py
dependency_injection/decorators/autowired.py
dependency_injection/decorators/autowired_enums.py
dependency_injection/decorators/autowired_handler.py
dependency_injection/decorators/component.py
dependency_injection/decorators/lock_once.py
dependency_injection/decorators/synchronized.py
dependency_injection/design_patterns/__init__.py
dependency_injection/design_patterns/singleton.py
dependency_injection/design_patterns/singleton_handler.py
dependency_injection/test_dependency_injection/Inject_abstract_muli_inherit.py
dependency_injection/test_dependency_injection/__init__.py
dependency_injection/test_dependency_injection/injected_abstract.py
dependency_injection/test_dependency_injection/injected_class1.py
dependency_injection/test_dependency_injection/injected_class2.py
dependency_injection/test_dependency_injection/test_abstract_class.py
dependency_injection/test_dependency_injection/test_abstract_class_multi.py
dependency_injection/test_dependency_injection/test_class_no_type_hint.py
dependency_injection/test_dependency_injection/test_class_singlecall.py
dependency_injection/test_dependency_injection/test_class_singleton.py
dependency_injection/test_dependency_injection/test_injection.py
python_dependency_injection-0.8.dist-info/LICENSE
python_dependency_injection-0.8.dist-info/METADATA
python_dependency_injection-0.8.dist-info/WHEEL
python_dependency_injection-0.8.dist-info/top_level.txt
python_dependency_injection-0.8.dist-info/RECORD
