Metadata-Version: 2.1
Name: python-dependency-injection
Version: 0.8
Summary: Python-dependency-injection is a simple yet powerful mini-framework for dependency injection in Python
Home-page: https://github.com/emalka/python-dependency-injection
Author: Eli Malka
Author-email: eli.malka.mail@gmail.com
License: MIT
Keywords: python dependency injection
Platform: UNKNOWN
Classifier: Development Status :: 4 - Beta
Classifier: Topic :: Utilities
Classifier: License :: OSI Approved :: MIT License
Classifier: Programming Language :: Python :: 3.6
Classifier: Operating System :: OS Independent
